{
	"1": {
		"b5ada5": "d4693b",
		"529cf7": "29b397",
		"4273ad": "16784f",
		"ef5252": "a0451a",
		"ffe65a": "ea9260",
		"ce3131": "672e32",
		"635a5a": "953408",
		"dedede": "f6a12d",
		"8c2929": "350f3d",
		"7b5a31": "731105",
		"f79c19": "d04215"
	},
	"2": {
		"b5ada5": "d4693b",
		"529cf7": "ce3131",
		"4273ad": "8c2929",
		"ef5252": "1fb869",
		"ffe65a": "4ef6f5",
		"ce3131": "2d8f72",
		"635a5a": "953408",
		"dedede": "ec932e",
		"8c2929": "0e4949",
		"7b5a31": "2a63a6",
		"f79c19": "3ca2da"
	}
}